pyonear-0.1.0.dist-info/METADATA
pyonear-0.1.0.dist-info/WHEEL
pyonear-0.1.0.dist-info/license_files/LICENSE
pyonear/account.pyi
pyonear/account_id.pyi
pyonear/config.pyi
pyonear/crypto.pyi
pyonear/crypto_hash.pyi
pyonear/error/core.pyi
pyonear/error/exception.pyi
pyonear/error/vm.pyi
pyonear/error/__init__.pyi
pyonear/merkle.pyi
pyonear/py.typed
pyonear/transaction.pyi
pyonear/__init__.py
pyonear/pyonear.pyd
pyonear-0.1.0.dist-info/RECORD
