Metadata-Version: 2.1
Name: pyonear
Version: 0.1.0
Classifier: Programming Language :: Rust
Classifier: Programming Language :: Python :: Implementation :: CPython
Classifier: Programming Language :: Python :: Implementation :: PyPy
License-File: LICENSE
Summary: Python bindings for NEAR Rust primitives.
Author-email: kevinheavey <notanemail@gmail.com>
License: MIT
Requires-Python: >=3.7
Project-URL: changelog, https://github.com/kevinheavey/pyonear/blob/main/CHANGELOG.md
Project-URL: documentation, https://kevinheavey.github.io/pyonear/
Project-URL: repository, https://github.com/kevinheavey/pyonear
Project-URL: homepage, https://github.com/kevinheavey/pyonear
